safwaText/__init__.py
safwaText/cleaner.py
safwaText/stemmer.py
safwaText/stopwords.py
safwaText-0.1.0.dist-info/LICENSE
safwaText-0.1.0.dist-info/METADATA
safwaText-0.1.0.dist-info/WHEEL
safwaText-0.1.0.dist-info/top_level.txt
safwaText-0.1.0.dist-info/RECORD
