Metadata-Version: 2.2
Name: safwaText
Version: 0.1.0
Summary: A Python package for Arabic text preprocessing, including cleaning, normalization, stemming, and stopword removal.
Author: Oussama Ben Slama
Author-email: Oussama Ben Slama <hello@ben-slama.tn>
License:                                  Apache License
Project-URL: Homepage, https://github.com/OussamaBenSlama/safwaText
Project-URL: Repository, https://github.com/OussamaBenSlama/safwaText/
Keywords: arabic,text-processing,nlp,stemming,normalization
Classifier: Development Status :: 4 - Beta
Classifier: Intended Audience :: Developers
Classifier: Intended Audience :: Science/Research
Classifier: License :: OSI Approved :: Apache Software License
Classifier: Programming Language :: Python :: 3
Classifier: Programming Language :: Python :: 3.6
Classifier: Programming Language :: Python :: 3.7
Classifier: Programming Language :: Python :: 3.8
Classifier: Programming Language :: Python :: 3.9
Classifier: Programming Language :: Python :: 3.10
Classifier: Programming Language :: Python :: 3.11
Classifier: Programming Language :: Python :: 3.12
Classifier: Topic :: Text Processing :: Linguistic
Classifier: Topic :: Software Development :: Libraries :: Python Modules
Requires-Python: >=3.6
License-File: LICENSE
Dynamic: author
Dynamic: requires-python
